milea_demo/__init__.py
milea_demo/admin.py
milea_demo/apps.py
milea_demo/models.py
milea_demo/notify.py
milea_demo/settings.py
milea_demo/tests.py
milea_demo/migrations/0001_initial.py
milea_demo/migrations/0002_initial.py
milea_demo/migrations/0003_alter_defaultmodal_progress.py
milea_demo/migrations/0004_defaultmodal_multiple.py
milea_demo/migrations/__init__.py
milea_demo/migrations/__pycache__/0001_initial.cpython-312.pyc
milea_demo/migrations/__pycache__/0002_initial.cpython-312.pyc
milea_demo/migrations/__pycache__/0003_alter_defaultmodal_progress.cpython-312.pyc
milea_demo/migrations/__pycache__/0004_defaultmodal_multiple.cpython-312.pyc
milea_demo/migrations/__pycache__/__init__.cpython-312.pyc
milea_demo-0.3.dist-info/METADATA
milea_demo-0.3.dist-info/WHEEL
milea_demo-0.3.dist-info/top_level.txt
milea_demo-0.3.dist-info/RECORD
